audiogen_mcp/__init__.py
audiogen_mcp/server.py
audiogen_mcp-0.2.1.dist-info/METADATA
audiogen_mcp-0.2.1.dist-info/WHEEL
audiogen_mcp-0.2.1.dist-info/entry_points.txt
audiogen_mcp-0.2.1.dist-info/licenses/LICENSE
audiogen_mcp-0.2.1.dist-info/RECORD
