Metadata-Version: 2.4
Name: audiogen-mcp
Version: 0.2.1
Summary: MCP server for generating sound effects using Meta's AudioGen
Project-URL: Homepage, https://github.com/peerjakobsen/audiogen-mcp
Project-URL: Repository, https://github.com/peerjakobsen/audiogen-mcp
Project-URL: Issues, https://github.com/peerjakobsen/audiogen-mcp/issues
Author: Peer Jakobsen
License: MIT
License-File: LICENSE
Keywords: ai,audio,audiogen,claude,mcp,sound-effects
Classifier: Development Status :: 4 - Beta
Classifier: Intended Audience :: Developers
Classifier: License :: OSI Approved :: MIT License
Classifier: Operating System :: MacOS
Classifier: Programming Language :: Python :: 3
Classifier: Programming Language :: Python :: 3.9
Classifier: Programming Language :: Python :: 3.10
Classifier: Programming Language :: Python :: 3.11
Classifier: Topic :: Multimedia :: Sound/Audio
Classifier: Topic :: Scientific/Engineering :: Artificial Intelligence
Requires-Python: <3.12,>=3.9
Requires-Dist: mcp>=1.0.0
Requires-Dist: scipy>=1.11.0
Requires-Dist: torch>=2.1.0
Requires-Dist: torchaudio>=2.1.0
